{"academicUnit":"Physics & Materials Science","code":"GE1309","exclusiveCourses":[],"prerequisites":null,"prerequisitesPostfix":[],"registrationDetail":[{"cohort":"2014","headcount":1,"major":"LLA","programme":"BA4"},{"cohort":"2013","headcount":1,"major":"LLT","programme":"BA4"},{"cohort":"2013","headcount":1,"major":"TI","programme":"BA4"},{"cohort":"2013","headcount":1,"major":"NEM","programme":"BAS4"},{"cohort":"2014","headcount":1,"major":"NEM","programme":"BAS4"},{"cohort":"2012","headcount":1,"major":"AC","programme":"BBA4"},{"cohort":"2013","headcount":1,"major":"BANL","programme":"BBA4"},{"cohort":"2014","headcount":3,"major":"BE","programme":"BBA4"},{"cohort":"2012","headcount":1,"major":"CB","programme":"BBA4"},{"cohort":"2014","headcount":1,"major":"CB","programme":"BBA4"},{"cohort":"2012","headcount":1,"major":"FIN","programme":"BBA4"},{"cohort":"2014","headcount":2,"major":"FIN","programme":"BBA4"},{"cohort":"2012","headcount":1,"major":"IFMG","programme":"BBA4"},{"cohort":"2012","headcount":2,"major":"MKT","programme":"BBA4"},{"cohort":"2014","headcount":3,"major":"MKT1","programme":"BBA4"},{"cohort":"2015","headcount":3,"major":"U","programme":"BBAU4"},{"cohort":"2015","headcount":3,"major":"U","programme":"BDAP"},{"cohort":"2015","headcount":1,"major":"U","programme":"BDCA"},{"cohort":"2015","headcount":5,"major":"U","programme":"BDCLASS"},{"cohort":"2015","headcount":2,"major":"U","programme":"BDEE"},{"cohort":"2015","headcount":1,"major":"U","programme":"BDMBE"},{"cohort":"2015","headcount":2,"major":"U","programme":"BDSCM"},{"cohort":"2014","headcount":1,"major":"MAE","programme":"BENG2"},{"cohort":"2014","headcount":1,"major":"BSE","programme":"BENG3"},{"cohort":"2013","headcount":1,"major":"ELTM","programme":"BENG3"},{"cohort":"2013","headcount":1,"major":"MAE","programme":"BENG3"},{"cohort":"2013","headcount":1,"major":"MTE","programme":"BENG3"},{"cohort":"2013","headcount":5,"major":"BSE","programme":"BENG4"},{"cohort":"2014","headcount":1,"major":"CE","programme":"BENG4"},{"cohort":"2013","headcount":1,"major":"CEM","programme":"BENG4"},{"cohort":"2012","headcount":1,"major":"CVSE","programme":"BENG4"},{"cohort":"2013","headcount":1,"major":"CVSE","programme":"BENG4"},{"cohort":"2012","headcount":8,"major":"MAE","programme":"BENG4"},{"cohort":"2013","headcount":1,"major":"MFSE","programme":"BENG4"},{"cohort":"2014","headcount":2,"major":"ESE","programme":"BENGSEE4"},{"cohort":"2015","headcount":1,"major":"BSE","programme":"BENGU2"},{"cohort":"2015","headcount":1,"major":"CVSE","programme":"BENGU2"},{"cohort":"2015","headcount":1,"major":"MAE","programme":"BENGU3"},{"cohort":"2014","headcount":2,"major":"AP","programme":"BSC2"},{"cohort":"2013","headcount":1,"major":"AB","programme":"BSC3"},{"cohort":"2012","headcount":1,"major":"AB","programme":"BSC4"},{"cohort":"2012","headcount":1,"major":"ACHM","programme":"BSC4"},{"cohort":"2012","headcount":1,"major":"CM","programme":"BSC4"},{"cohort":"2012","headcount":1,"major":"CSC","programme":"BSC4"},{"cohort":"2013","headcount":1,"major":"CRM1","programme":"BSCSCM4"},{"cohort":"2015","headcount":1,"major":"ACHM","programme":"BSCU2"},{"cohort":"2015","headcount":2,"major":"SURV","programme":"BSCU2"},{"cohort":"2015","headcount":2,"major":"CM","programme":"BSCU4"},{"cohort":"2012","headcount":1,"major":"ASIS","programme":"BSS4"},{"cohort":"2012","headcount":1,"major":"ASOC","programme":"BSS4"},{"cohort":"2014","headcount":1,"major":"ENP","programme":"BSS4"},{"cohort":"2014","headcount":2,"major":"PP","programme":"BSS4"},{"cohort":"2012","headcount":2,"major":"PPMP","programme":"BSS4"},{"cohort":"2013","headcount":2,"major":"PPMP","programme":"BSS4"},{"cohort":"2014","headcount":1,"major":"PSY","programme":"BSS4"},{"cohort":"2015","headcount":1,"major":"PP","programme":"BSSU3"},{"cohort":"2015","headcount":5,"major":"0000","programme":"ELAC"},{"cohort":"0000","headcount":1,"major":"0000","programme":"EXGB"},{"cohort":"2013","headcount":1,"major":"LW","programme":"LLB4"}],"sections":[{"availableSeats":8,"availableWaitlistQuota":0,"campus":"Main Campus","capacity":105,"credit":3,"crn":46164,"groups":[{"building":"AC2","date":["2016-01-10T16:00:00.000Z","2016-04-23T15:59:59.999Z"],"day":["R"],"instructors":["VELLAISAMY Arul Lenus Roy","SEEMANN Frauke","WONG Chung Kai J."],"mediumOfInstruction":null,"notForCollege":[],"notForDegree":[],"notForMajor":[],"notForProgramme":[],"notes":[],"onlyForCollege":[],"onlyForDegree":[],"onlyForMajor":[],"onlyForProgramme":[],"room":"3508","time":["15:00","16:50"]}],"levels":["B"],"section":"C01","waitlistAvailable":"N","webEnabled":true},{"availableSeats":8,"availableWaitlistQuota":0,"campus":"Main Campus","capacity":105,"credit":0,"crn":46165,"groups":[{"building":"AC2","date":["2016-01-10T16:00:00.000Z","2016-04-23T15:59:59.999Z"],"day":["R"],"instructors":["VELLAISAMY Arul Lenus Roy","PEI Zengxia","SUN Qijun","WONG Chung Kai J.","SEEMANN Frauke"],"mediumOfInstruction":null,"notForCollege":[],"notForDegree":[],"notForMajor":[],"notForProgramme":[],"notes":[],"onlyForCollege":[],"onlyForDegree":[],"onlyForMajor":[],"onlyForProgramme":[],"room":"3508","time":["17:00","17:50"]}],"levels":["B"],"section":"T01","waitlistAvailable":"N","webEnabled":true}],"title":"Science in Chinese Kung Fu"}