{"academicUnit":"Applied Social Sciences","code":"GE2109","exclusiveCourses":[],"prerequisites":null,"prerequisitesPostfix":[],"registrationDetail":[{"cohort":"2012","headcount":35,"major":"SW1","programme":"BA2"},{"cohort":"2013","headcount":2,"major":"SW1","programme":"BA2"},{"cohort":"2011","headcount":1,"major":"AC","programme":"BBA3"},{"cohort":"2012","headcount":1,"major":"AC","programme":"BBA3"},{"cohort":"2011","headcount":2,"major":"BE","programme":"BBA3"},{"cohort":"2011","headcount":1,"major":"IFMG","programme":"BBA3"},{"cohort":"2013","headcount":1,"major":"MKT","programme":"BBA3"},{"cohort":"2011","headcount":1,"major":"SOM","programme":"BBA3"},{"cohort":"2010","headcount":1,"major":"ECE","programme":"BEECE"},{"cohort":"2013","headcount":1,"major":"CEM","programme":"BENG2"},{"cohort":"2011","headcount":1,"major":"CE","programme":"BENG3"},{"cohort":"2011","headcount":5,"major":"ECE","programme":"BENG3"},{"cohort":"2011","headcount":1,"major":"INFE","programme":"BENG3"},{"cohort":"2011","headcount":3,"major":"MAE","programme":"BENG3"},{"cohort":"2011","headcount":2,"major":"CSC","programme":"BSCCS"},{"cohort":"2012","headcount":1,"major":"CRM1","programme":"BSCSCM3"},{"cohort":"2012","headcount":1,"major":"ENP","programme":"BSS3"}],"sections":[{"availableSeats":0,"availableWaitlistQuota":0,"campus":"Main Campus","capacity":60,"credit":3,"crn":16253,"groups":[{"building":"AC2","date":["2014-06-08T16:00:00.000Z","2014-07-26T15:59:59.999Z"],"day":["T"],"instructors":["LEUNG LING Tien Wei Mary"],"mediumOfInstruction":null,"notForCollege":[],"notForDegree":[],"notForMajor":[],"notForProgramme":[],"notes":[],"onlyForCollege":[],"onlyForDegree":[],"onlyForMajor":[],"onlyForProgramme":[],"room":"1601","time":["19:00","21:50"]},{"building":"AC2","date":["2014-06-08T16:00:00.000Z","2014-07-26T15:59:59.999Z"],"day":["R"],"instructors":["LEUNG LING Tien Wei Mary"],"mediumOfInstruction":null,"notForCollege":[],"notForDegree":[],"notForMajor":[],"notForProgramme":[],"notes":[],"onlyForCollege":[],"onlyForDegree":[],"onlyForMajor":[],"onlyForProgramme":[],"room":"1601","time":["19:00","21:50"]}],"levels":["B"],"section":"C61","waitlistAvailable":"N","webEnabled":true}],"title":"Love, Sex, and Relationships: Psychological Perspectives"}