{"academicUnit":"Electronic Engineering","code":"GE1331","exclusiveCourses":[],"prerequisites":null,"prerequisitesPostfix":[],"registrationDetail":[{"cohort":"2012","headcount":1,"major":"BE","programme":"BBA2"},{"cohort":"2012","headcount":1,"major":"IFMG","programme":"BBA2"},{"cohort":"2011","headcount":1,"major":"BE","programme":"BBA3"},{"cohort":"2011","headcount":1,"major":"FIN","programme":"BBA3"},{"cohort":"2011","headcount":1,"major":"MKT","programme":"BBA3"},{"cohort":"2012","headcount":2,"major":"MST","programme":"BBA3"},{"cohort":"2012","headcount":2,"major":"BANL","programme":"BBA4"},{"cohort":"2012","headcount":1,"major":"MGSC","programme":"BBA4"},{"cohort":"2013","headcount":3,"major":"U","programme":"BBA4"},{"cohort":"2013","headcount":1,"major":"BE","programme":"BBAN2"},{"cohort":"2013","headcount":3,"major":"U","programme":"BDCLASS"},{"cohort":"2013","headcount":2,"major":"U","programme":"BDSCM"},{"cohort":"2009","headcount":1,"major":"CE","programme":"BECE"},{"cohort":"2013","headcount":1,"major":"INFE","programme":"BENG2"},{"cohort":"2011","headcount":8,"major":"CE","programme":"BENG3"},{"cohort":"2012","headcount":6,"major":"CE","programme":"BENG3"},{"cohort":"2011","headcount":2,"major":"ECE","programme":"BENG3"},{"cohort":"2012","headcount":6,"major":"ECE","programme":"BENG3"},{"cohort":"2012","headcount":1,"major":"ELTM","programme":"BENG3"},{"cohort":"2011","headcount":4,"major":"INFE","programme":"BENG3"},{"cohort":"2012","headcount":1,"major":"INFE","programme":"BENG3"},{"cohort":"2013","headcount":3,"major":"INFE","programme":"BENG3"},{"cohort":"2012","headcount":6,"major":"MTE","programme":"BENG3"},{"cohort":"2012","headcount":4,"major":"CE","programme":"BENG4"},{"cohort":"2012","headcount":2,"major":"CVSE","programme":"BENG4"},{"cohort":"2012","headcount":4,"major":"INFE","programme":"BENG4"},{"cohort":"2013","headcount":12,"major":"U","programme":"BENG4"},{"cohort":"2011","headcount":1,"major":"AB","programme":"BSC3"},{"cohort":"2012","headcount":2,"major":"CSC","programme":"BSC3"},{"cohort":"2012","headcount":4,"major":"CSC","programme":"BSC4"},{"cohort":"2013","headcount":2,"major":"U","programme":"BSC4"},{"cohort":"2010","headcount":7,"major":"CSC","programme":"BSCCS"},{"cohort":"2011","headcount":1,"major":"CSC","programme":"BSCCS"},{"cohort":"2012","headcount":1,"major":"CRM1","programme":"BSCSCM4"},{"cohort":"2012","headcount":1,"major":"PPMP","programme":"BSS4"},{"cohort":"2012","headcount":1,"major":"LW","programme":"LLB4"}],"sections":[{"availableSeats":0,"availableWaitlistQuota":0,"campus":"Main Campus","capacity":100,"credit":3,"crn":43092,"groups":[{"building":"AC2","date":["2014-01-12T16:00:00.000Z","2014-04-26T15:59:59.999Z"],"day":["W"],"instructors":["WU Kwok Ming A."],"mediumOfInstruction":null,"notForCollege":[],"notForDegree":[],"notForMajor":[],"notForProgramme":[],"notes":[],"onlyForCollege":[],"onlyForDegree":[],"onlyForMajor":[],"onlyForProgramme":[],"room":"G600","time":["14:00","16:50"]}],"levels":["B"],"section":"C01","waitlistAvailable":"N","webEnabled":true}],"title":"Problem Solving Made Easy"}