{"academicUnit":"Physics & Materials Science","code":"GE1309","exclusiveCourses":[],"prerequisites":null,"prerequisitesPostfix":[],"registrationDetail":[{"cohort":"2013","headcount":1,"major":"LGS1","programme":"BA2"},{"cohort":"2012","headcount":1,"major":"MDCM","programme":"BA3"},{"cohort":"2012","headcount":1,"major":"TI","programme":"BA3"},{"cohort":"2012","headcount":1,"major":"AC","programme":"BBA2"},{"cohort":"2012","headcount":2,"major":"CB","programme":"BBA2"},{"cohort":"2012","headcount":1,"major":"FIN","programme":"BBA2"},{"cohort":"2012","headcount":1,"major":"HRM","programme":"BBA2"},{"cohort":"2012","headcount":1,"major":"IFMG","programme":"BBA2"},{"cohort":"2012","headcount":1,"major":"AC","programme":"BBA3"},{"cohort":"2011","headcount":1,"major":"FIN","programme":"BBA3"},{"cohort":"2011","headcount":1,"major":"HRM","programme":"BBA3"},{"cohort":"2013","headcount":1,"major":"IFMG","programme":"BBA3"},{"cohort":"2011","headcount":1,"major":"MKT","programme":"BBA3"},{"cohort":"2012","headcount":4,"major":"MKT","programme":"BBA3"},{"cohort":"2012","headcount":2,"major":"MSCI","programme":"BBA3"},{"cohort":"2011","headcount":1,"major":"QFRM","programme":"BBA3"},{"cohort":"2011","headcount":1,"major":"SOM","programme":"BBA3"},{"cohort":"2012","headcount":1,"major":"SOM","programme":"BBA3"},{"cohort":"2012","headcount":1,"major":"AC","programme":"BBA4"},{"cohort":"2012","headcount":1,"major":"BANL","programme":"BBA4"},{"cohort":"2012","headcount":4,"major":"BE","programme":"BBA4"},{"cohort":"2012","headcount":2,"major":"BFS","programme":"BBA4"},{"cohort":"2012","headcount":2,"major":"FIN","programme":"BBA4"},{"cohort":"2012","headcount":1,"major":"GBSM","programme":"BBA4"},{"cohort":"2012","headcount":1,"major":"IBJ","programme":"BBA4"},{"cohort":"2012","headcount":1,"major":"IFMG","programme":"BBA4"},{"cohort":"2013","headcount":4,"major":"U","programme":"BBA4"},{"cohort":"2013","headcount":1,"major":"CB","programme":"BBAN2"},{"cohort":"2012","headcount":1,"major":"HRM","programme":"BBAN2"},{"cohort":"2013","headcount":1,"major":"HRM","programme":"BBAN2"},{"cohort":"2013","headcount":3,"major":"U","programme":"BDCLASS"},{"cohort":"2013","headcount":2,"major":"U","programme":"BDSCM"},{"cohort":"2011","headcount":1,"major":"CE","programme":"BENG3"},{"cohort":"2011","headcount":1,"major":"INFE","programme":"BENG3"},{"cohort":"2011","headcount":5,"major":"MAE","programme":"BENG3"},{"cohort":"2012","headcount":2,"major":"MAE","programme":"BENG3"},{"cohort":"2012","headcount":1,"major":"CVSE","programme":"BENG4"},{"cohort":"2012","headcount":3,"major":"INFE","programme":"BENG4"},{"cohort":"2012","headcount":1,"major":"MAE","programme":"BENG4"},{"cohort":"2013","headcount":16,"major":"U","programme":"BENG4"},{"cohort":"2012","headcount":1,"major":"ACHM","programme":"BSC2"},{"cohort":"2011","headcount":1,"major":"ACHM","programme":"BSC3"},{"cohort":"2012","headcount":5,"major":"ACHM","programme":"BSC3"},{"cohort":"2012","headcount":2,"major":"AP","programme":"BSC3"},{"cohort":"2012","headcount":1,"major":"CSC","programme":"BSC3"},{"cohort":"2011","headcount":1,"major":"ESM","programme":"BSC3"},{"cohort":"2012","headcount":1,"major":"ESM","programme":"BSC3"},{"cohort":"2013","headcount":2,"major":"ESM","programme":"BSC3"},{"cohort":"2012","headcount":3,"major":"ACHM","programme":"BSC4"},{"cohort":"2013","headcount":1,"major":"U","programme":"BSC4"},{"cohort":"2010","headcount":1,"major":"CSC","programme":"BSCCS"},{"cohort":"2011","headcount":2,"major":"CM","programme":"BSCM"},{"cohort":"2012","headcount":1,"major":"APM","programme":"BSS2"},{"cohort":"2012","headcount":2,"major":"PPMP","programme":"BSS3"},{"cohort":"2012","headcount":8,"major":"SW","programme":"BSS3"},{"cohort":"2012","headcount":1,"major":"ENP","programme":"BSS4"},{"cohort":"2012","headcount":1,"major":"PPMP","programme":"BSS4"},{"cohort":"2012","headcount":1,"major":"SW","programme":"BSS4"},{"cohort":"0000","headcount":1,"major":"0000","programme":"EXGB"},{"cohort":"2012","headcount":6,"major":"LW","programme":"LLB4"}],"sections":[{"availableSeats":0,"availableWaitlistQuota":0,"campus":"Main Campus","capacity":120,"credit":3,"crn":42002,"groups":[{"building":"AC1","date":["2014-01-12T16:00:00.000Z","2014-04-26T15:59:59.999Z"],"day":["M"],"instructors":["VELLAISAMY Arul Lenus Roy"],"mediumOfInstruction":null,"notForCollege":[],"notForDegree":[],"notForMajor":[],"notForProgramme":[],"notes":[],"onlyForCollege":[],"onlyForDegree":[],"onlyForMajor":[],"onlyForProgramme":[],"room":"LT-12","time":["11:00","12:50"]}],"levels":["B"],"section":"C01","waitlistAvailable":"N","webEnabled":true},{"availableSeats":0,"availableWaitlistQuota":0,"campus":"Main Campus","capacity":120,"credit":0,"crn":42003,"groups":[{"building":"AC1","date":["2014-01-12T16:00:00.000Z","2014-04-26T15:59:59.999Z"],"day":["M"],"instructors":["VELLAISAMY Arul Lenus Roy","HUANG Longbiao"],"mediumOfInstruction":null,"notForCollege":[],"notForDegree":[],"notForMajor":[],"notForProgramme":[],"notes":[],"onlyForCollege":[],"onlyForDegree":[],"onlyForMajor":[],"onlyForProgramme":[],"room":"LT-12","time":["13:00","13:50"]}],"levels":["B"],"section":"T01","waitlistAvailable":"N","webEnabled":true}],"title":"Science in Chinese Kung Fu"}