{"academicUnit":"Mechanical and Biomedical Engg","code":"GE2301","exclusiveCourses":[],"prerequisites":null,"prerequisitesPostfix":[],"registrationDetail":[{"cohort":"2016","headcount":2,"major":"AS2","programme":"ASC"},{"cohort":"2016","headcount":5,"major":"BSE2","programme":"ASC"},{"cohort":"2016","headcount":3,"major":"SUR2","programme":"ASC"},{"cohort":"2014","headcount":1,"major":"LLA","programme":"BA4"},{"cohort":"2013","headcount":1,"major":"CRM","programme":"BASCM4"},{"cohort":"2015","headcount":1,"major":"CRM","programme":"BASCMU4"},{"cohort":"2013","headcount":1,"major":"AC","programme":"BBA4"},{"cohort":"2013","headcount":1,"major":"BANL","programme":"BBA4"},{"cohort":"2014","headcount":1,"major":"BFS","programme":"BBA4"},{"cohort":"2015","headcount":1,"major":"AC","programme":"BBAU4"},{"cohort":"2015","headcount":1,"major":"BE1","programme":"BBAU4"},{"cohort":"2015","headcount":1,"major":"CB","programme":"BBAU4"},{"cohort":"2016","headcount":1,"major":"MKT1","programme":"BBAU4"},{"cohort":"2014","headcount":1,"major":"MAE","programme":"BENG3"},{"cohort":"2013","headcount":1,"major":"ECE","programme":"BENG4"},{"cohort":"2013","headcount":1,"major":"MAE","programme":"BENG4"},{"cohort":"2014","headcount":1,"major":"MAE","programme":"BENG4"},{"cohort":"2016","headcount":1,"major":"CDE","programme":"BENGU2"},{"cohort":"2016","headcount":4,"major":"MAE","programme":"BENGU2"},{"cohort":"2016","headcount":2,"major":"CDE","programme":"BENGU3"},{"cohort":"2016","headcount":1,"major":"MTE","programme":"BENGU3"},{"cohort":"2016","headcount":1,"major":"SEM","programme":"BENGU4"},{"cohort":"2013","headcount":1,"major":"AP","programme":"BSC4"},{"cohort":"2013","headcount":1,"major":"CRM1","programme":"BSCSCM4"},{"cohort":"2014","headcount":1,"major":"CRM1","programme":"BSCSCM4"},{"cohort":"2016","headcount":1,"major":"AB","programme":"BSCU2"},{"cohort":"2016","headcount":1,"major":"CSC","programme":"BSCU2"},{"cohort":"2015","headcount":1,"major":"CSC","programme":"BSCU4"},{"cohort":"2014","headcount":1,"major":"ENP","programme":"BSS3"},{"cohort":"2014","headcount":1,"major":"PP","programme":"BSS4"}],"sections":[{"availableSeats":49,"availableWaitlistQuota":0,"campus":"Main Campus","capacity":90,"credit":3,"crn":10326,"groups":[{"building":"AC1","date":["2017-06-04T16:00:00.000Z","2017-07-22T15:59:59.999Z"],"day":["F"],"instructors":["HUA Meng","LUK Bing Lam","LOCK Fat Shing L."],"mediumOfInstruction":"English","notForCollege":[],"notForDegree":[],"notForMajor":[],"notForProgramme":[],"notes":[],"onlyForCollege":[],"onlyForDegree":[],"onlyForMajor":[],"onlyForProgramme":[],"room":"LT-17","time":["09:00","11:50"]},{"building":"AC1","date":["2017-06-04T16:00:00.000Z","2017-07-22T15:59:59.999Z"],"day":["W"],"instructors":["HUA Meng","LUK Bing Lam","LOCK Fat Shing L."],"mediumOfInstruction":"English","notForCollege":[],"notForDegree":[],"notForMajor":[],"notForProgramme":[],"notes":[],"onlyForCollege":[],"onlyForDegree":[],"onlyForMajor":[],"onlyForProgramme":[],"room":"LT-17","time":["14:00","16:50"]}],"levels":["A","B"],"section":"C01","waitlistAvailable":"N","webEnabled":true}],"title":"Science and Technology: From Past to Future"}