{"academicUnit":"Chinese Civilisation Centre","code":"GE1106","exclusiveCourses":[],"prerequisites":null,"prerequisitesPostfix":[],"registrationDetail":[{"cohort":"2012","headcount":5,"major":"U","programme":"ASC"},{"cohort":"2012","headcount":1,"major":"ELST","programme":"BA2"},{"cohort":"2012","headcount":1,"major":"ISC","programme":"BA2"},{"cohort":"2011","headcount":2,"major":"LLT","programme":"BA2"},{"cohort":"2010","headcount":1,"major":"LLT","programme":"BA3"},{"cohort":"2011","headcount":1,"major":"CHIN","programme":"BACH"},{"cohort":"2011","headcount":1,"major":"CHM","programme":"BACHM"},{"cohort":"2010","headcount":1,"major":"DMB","programme":"BADMB"},{"cohort":"2011","headcount":1,"major":"MDCM","programme":"BAMC"},{"cohort":"2012","headcount":1,"major":"NEM","programme":"BAS3"},{"cohort":"2011","headcount":3,"major":"CRM","programme":"BASCM2"},{"cohort":"2012","headcount":1,"major":"CRM","programme":"BASCM2"},{"cohort":"2010","headcount":1,"major":"CRM","programme":"BASCM3"},{"cohort":"2012","headcount":3,"major":"CRM","programme":"BASCM3"},{"cohort":"2012","headcount":1,"major":"AC","programme":"BBA3"},{"cohort":"2011","headcount":1,"major":"GBSM","programme":"BBA3"},{"cohort":"2012","headcount":1,"major":"IFMG","programme":"BBA3"},{"cohort":"2011","headcount":2,"major":"MST","programme":"BBA3"},{"cohort":"2012","headcount":6,"major":"U","programme":"BBA4"},{"cohort":"2009","headcount":1,"major":"IBJ","programme":"BBAIBJ"},{"cohort":"2009","headcount":1,"major":"MKT","programme":"BBAMKT"},{"cohort":"2012","headcount":3,"major":"U","programme":"BDCLASS"},{"cohort":"2012","headcount":2,"major":"U","programme":"BDSCM"},{"cohort":"2012","headcount":1,"major":"U","programme":"BDSEE"},{"cohort":"2011","headcount":2,"major":"ELTM","programme":"BEELTM"},{"cohort":"2011","headcount":6,"major":"MFSE","programme":"BEMSE"},{"cohort":"2011","headcount":1,"major":"ECE","programme":"BENG3"},{"cohort":"2012","headcount":3,"major":"U","programme":"BENG4"},{"cohort":"2011","headcount":3,"major":"TQE","programme":"BETQE"},{"cohort":"2011","headcount":1,"major":"ESM","programme":"BSC2"},{"cohort":"2010","headcount":1,"major":"AB","programme":"BSC3"},{"cohort":"2012","headcount":1,"major":"CSC","programme":"BSC3"},{"cohort":"2010","headcount":2,"major":"ESM","programme":"BSC3"},{"cohort":"2010","headcount":1,"major":"APM","programme":"BSSAPM"},{"cohort":"2011","headcount":2,"major":"SW","programme":"BSSSW"},{"cohort":"2012","headcount":2,"major":"0000","programme":"ELAC"},{"cohort":"0000","headcount":3,"major":"0000","programme":"EXGB"},{"cohort":"2008","headcount":1,"major":"LLB","programme":"LLB3"}],"sections":[{"availableSeats":2,"availableWaitlistQuota":0,"campus":"Main Campus","capacity":52,"credit":3,"crn":33719,"groups":[{"building":"AC1","date":["2012-09-09T16:00:00.000Z","2012-12-08T15:59:59.999Z"],"day":["F"],"instructors":["CHUI Lisa L S","WONG Marianne P Y"],"mediumOfInstruction":null,"notForCollege":[],"notForDegree":[],"notForMajor":[],"notForProgramme":[],"notes":[],"onlyForCollege":[],"onlyForDegree":[],"onlyForMajor":[],"onlyForProgramme":[],"room":"G5-317","time":["09:00","10:50"]}],"levels":["A","B"],"section":"CA1","waitlistAvailable":"N","webEnabled":true},{"availableSeats":4,"availableWaitlistQuota":0,"campus":"Main Campus","capacity":25,"credit":3,"crn":33723,"groups":[{"building":"CYC","date":["2012-09-09T16:00:00.000Z","2012-12-08T15:59:59.999Z"],"day":["W"],"instructors":["WONG Marianne P Y"],"mediumOfInstruction":null,"notForCollege":[],"notForDegree":[],"notForMajor":[],"notForProgramme":[],"notes":[],"onlyForCollege":[],"onlyForDegree":[],"onlyForMajor":[],"onlyForProgramme":[],"room":"CY-301","time":["15:00","16:50"]}],"levels":["A","B"],"section":"CB1","waitlistAvailable":"N","webEnabled":true},{"availableSeats":2,"availableWaitlistQuota":0,"campus":"Main Campus","capacity":27,"credit":0,"crn":33724,"groups":[{"building":"AC1","date":["2012-09-09T16:00:00.000Z","2012-12-08T15:59:59.999Z"],"day":["F"],"instructors":["WONG Marianne P Y"],"mediumOfInstruction":null,"notForCollege":[],"notForDegree":[],"notForMajor":[],"notForProgramme":[],"notes":[],"onlyForCollege":[],"onlyForDegree":[],"onlyForMajor":[],"onlyForProgramme":[],"room":"G5-317","time":["11:00","12:50"]}],"levels":["A","B"],"section":"TA1","waitlistAvailable":"N","webEnabled":true},{"availableSeats":0,"availableWaitlistQuota":0,"campus":"Main Campus","capacity":25,"credit":0,"crn":33725,"groups":[{"building":"AC1","date":["2012-09-09T16:00:00.000Z","2012-12-08T15:59:59.999Z"],"day":["F"],"instructors":["CHUI Lisa L S"],"mediumOfInstruction":null,"notForCollege":[],"notForDegree":[],"notForMajor":[],"notForProgramme":[],"notes":[],"onlyForCollege":[],"onlyForDegree":[],"onlyForMajor":[],"onlyForProgramme":[],"room":"Y5-405","time":["11:00","12:50"]}],"levels":["A","B"],"section":"TA2","waitlistAvailable":"N","webEnabled":true},{"availableSeats":4,"availableWaitlistQuota":0,"campus":"Main Campus","capacity":25,"credit":0,"crn":33727,"groups":[{"building":"CYC","date":["2012-09-09T16:00:00.000Z","2012-12-08T15:59:59.999Z"],"day":["W"],"instructors":["WONG Marianne P Y"],"mediumOfInstruction":null,"notForCollege":[],"notForDegree":[],"notForMajor":[],"notForProgramme":[],"notes":[],"onlyForCollege":[],"onlyForDegree":[],"onlyForMajor":[],"onlyForProgramme":[],"room":"CY-301","time":["17:00","18:50"]}],"levels":["A","B"],"section":"TB1","waitlistAvailable":"N","webEnabled":true}],"title":"Chinese Art Appreciation"}