{"academicUnit":"Electronic Engineering","code":"GE2318","exclusiveCourses":[],"prerequisites":null,"prerequisitesPostfix":[],"registrationDetail":[{"cohort":"2012","headcount":4,"major":"ELST","programme":"BA2"},{"cohort":"2011","headcount":1,"major":"EPC","programme":"BA2"},{"cohort":"2012","headcount":1,"major":"ISC","programme":"BA2"},{"cohort":"2010","headcount":1,"major":"LLT","programme":"BA3"},{"cohort":"2011","headcount":1,"major":"CRM","programme":"BASCM2"},{"cohort":"2010","headcount":1,"major":"CRM","programme":"BASCM3"},{"cohort":"2012","headcount":1,"major":"AC","programme":"BBA3"},{"cohort":"2011","headcount":1,"major":"BE","programme":"BBA3"},{"cohort":"2011","headcount":1,"major":"ECOM","programme":"BBA3"},{"cohort":"2011","headcount":1,"major":"FIN","programme":"BBA3"},{"cohort":"2011","headcount":1,"major":"GBSM","programme":"BBA3"},{"cohort":"2011","headcount":1,"major":"HRM","programme":"BBA3"},{"cohort":"2011","headcount":2,"major":"IFMG","programme":"BBA3"},{"cohort":"2011","headcount":1,"major":"MKT","programme":"BBA3"},{"cohort":"2012","headcount":1,"major":"MKT","programme":"BBA3"},{"cohort":"2011","headcount":1,"major":"MST","programme":"BBA3"},{"cohort":"2012","headcount":1,"major":"QFRM","programme":"BBA3"},{"cohort":"2012","headcount":2,"major":"U","programme":"BBA4"},{"cohort":"2010","headcount":1,"major":"FIN","programme":"BBAF"},{"cohort":"2010","headcount":1,"major":"ELTM","programme":"BEELTM"},{"cohort":"2010","headcount":1,"major":"IEEM","programme":"BEIEEM"},{"cohort":"2011","headcount":1,"major":"MFSE","programme":"BEMSE"},{"cohort":"2011","headcount":2,"major":"CE","programme":"BENG3"},{"cohort":"2012","headcount":1,"major":"CE","programme":"BENG3"},{"cohort":"2011","headcount":1,"major":"ECE","programme":"BENG3"},{"cohort":"2012","headcount":1,"major":"ECE","programme":"BENG3"},{"cohort":"2012","headcount":4,"major":"U","programme":"BENG4"},{"cohort":"2012","headcount":2,"major":"U","programme":"BSC4"},{"cohort":"2007","headcount":1,"major":"CSC","programme":"BSCCS"},{"cohort":"2011","headcount":2,"major":"CM","programme":"BSCM"},{"cohort":"2012","headcount":6,"major":"APM","programme":"BSS2"},{"cohort":"2012","headcount":1,"major":"ASIS","programme":"BSS2"},{"cohort":"2012","headcount":1,"major":"ASIS","programme":"BSS3"},{"cohort":"2012","headcount":7,"major":"0000","programme":"ELAC"}],"sections":[{"availableSeats":4,"availableWaitlistQuota":0,"campus":"Main Campus","capacity":60,"credit":3,"crn":38514,"groups":[{"building":"AC1","date":["2012-09-09T16:00:00.000Z","2012-12-08T15:59:59.999Z"],"day":["T"],"instructors":["CHEN Guanrong","MAN Kim Fung","TANG Kit Sang W."],"mediumOfInstruction":null,"notForCollege":[],"notForDegree":[],"notForMajor":[],"notForProgramme":[],"notes":[],"onlyForCollege":[],"onlyForDegree":[],"onlyForMajor":[],"onlyForProgramme":[],"room":"G5-314","time":["15:00","17:50"]}],"levels":["B"],"section":"C01","waitlistAvailable":"N","webEnabled":true}],"title":"From Ancient Wisdom to Modern Science"}