{"academicUnit":"Building Science & Technology","code":"GE1307","exclusiveCourses":[],"prerequisites":null,"prerequisitesPostfix":[],"registrationDetail":[{"cohort":"2012","headcount":8,"major":"AS","programme":"ASC"},{"cohort":"2012","headcount":2,"major":"BS1","programme":"ASC"},{"cohort":"2012","headcount":3,"major":"BSE","programme":"ASC"},{"cohort":"2012","headcount":1,"major":"CEM","programme":"ASC"},{"cohort":"2012","headcount":1,"major":"ES1","programme":"ASC"},{"cohort":"2012","headcount":4,"major":"QS1","programme":"ASC"},{"cohort":"2011","headcount":4,"major":"AS","programme":"ASCAS"},{"cohort":"2012","headcount":1,"major":"LGS1","programme":"BA2"},{"cohort":"2012","headcount":1,"major":"LLT","programme":"BA2"},{"cohort":"2012","headcount":1,"major":"MDCM","programme":"BA3"},{"cohort":"2009","headcount":4,"major":"HS","programme":"BAHS"},{"cohort":"2012","headcount":1,"major":"IBJ","programme":"BBA2"},{"cohort":"2011","headcount":1,"major":"AC","programme":"BBA3"},{"cohort":"2012","headcount":1,"major":"AC","programme":"BBA3"},{"cohort":"2011","headcount":1,"major":"BE","programme":"BBA3"},{"cohort":"2012","headcount":1,"major":"CB","programme":"BBA3"},{"cohort":"2012","headcount":3,"major":"FIN","programme":"BBA3"},{"cohort":"2012","headcount":2,"major":"GBSM","programme":"BBA3"},{"cohort":"2011","headcount":5,"major":"HRM","programme":"BBA3"},{"cohort":"2012","headcount":3,"major":"MKT","programme":"BBA3"},{"cohort":"2012","headcount":1,"major":"MST","programme":"BBA3"},{"cohort":"2011","headcount":1,"major":"QFRM","programme":"BBA3"},{"cohort":"2012","headcount":1,"major":"QFRM","programme":"BBA3"},{"cohort":"2012","headcount":1,"major":"U","programme":"BBA4"},{"cohort":"2010","headcount":1,"major":"IFMG","programme":"BBAIM"},{"cohort":"2012","headcount":2,"major":"HRM","programme":"BBAN2"},{"cohort":"2012","headcount":1,"major":"IFMG","programme":"BBAN2"},{"cohort":"2010","headcount":2,"major":"SGE","programme":"BEBESGE"},{"cohort":"2010","headcount":1,"major":"ECE","programme":"BEECE"},{"cohort":"2009","headcount":1,"major":"INFE","programme":"BEIE"},{"cohort":"2010","headcount":4,"major":"INFE","programme":"BEIE"},{"cohort":"2012","headcount":3,"major":"BSE","programme":"BENG3"},{"cohort":"2011","headcount":2,"major":"CE","programme":"BENG3"},{"cohort":"2012","headcount":2,"major":"CEM","programme":"BENG3"},{"cohort":"2012","headcount":8,"major":"ECE","programme":"BENG3"},{"cohort":"2012","headcount":1,"major":"INFE","programme":"BENG3"},{"cohort":"2012","headcount":1,"major":"MAE","programme":"BENG3"},{"cohort":"2012","headcount":1,"major":"U","programme":"BENG4"},{"cohort":"2012","headcount":8,"major":"AS","programme":"BSC2"},{"cohort":"2012","headcount":1,"major":"ESM","programme":"BSC3"},{"cohort":"2012","headcount":2,"major":"SURV","programme":"BSC3"},{"cohort":"2012","headcount":1,"major":"U","programme":"BSC4"},{"cohort":"2010","headcount":3,"major":"CSC","programme":"BSCCS"},{"cohort":"2010","headcount":1,"major":"CM","programme":"BSCM"},{"cohort":"2012","headcount":1,"major":"ASIS","programme":"BSS2"},{"cohort":"2012","headcount":1,"major":"ENP","programme":"BSS3"}],"sections":[{"availableSeats":0,"availableWaitlistQuota":0,"campus":"Main Campus","capacity":50,"credit":3,"crn":16058,"groups":[{"building":"AC2","date":["2013-06-09T16:00:00.000Z","2013-07-27T15:59:59.999Z"],"day":["S"],"instructors":["KWOK Che Shan"],"mediumOfInstruction":null,"notForCollege":[],"notForDegree":[],"notForMajor":[],"notForProgramme":[],"notes":[],"onlyForCollege":[],"onlyForDegree":[],"onlyForMajor":[],"onlyForProgramme":[],"room":"1301","time":["10:00","12:50"]},{"building":"AC2","date":["2013-06-09T16:00:00.000Z","2013-07-27T15:59:59.999Z"],"day":["T"],"instructors":["KWOK Che Shan"],"mediumOfInstruction":null,"notForCollege":[],"notForDegree":[],"notForMajor":[],"notForProgramme":[],"notes":[],"onlyForCollege":[],"onlyForDegree":[],"onlyForMajor":[],"onlyForProgramme":[],"room":"1301","time":["19:00","21:50"]}],"levels":["A","B"],"section":"C61","waitlistAvailable":"N","webEnabled":true},{"availableSeats":3,"availableWaitlistQuota":0,"campus":"Main Campus","capacity":53,"credit":3,"crn":16059,"groups":[{"building":"AC2","date":["2013-06-09T16:00:00.000Z","2013-07-27T15:59:59.999Z"],"day":["S"],"instructors":["KWOK Che Shan"],"mediumOfInstruction":null,"notForCollege":[],"notForDegree":[],"notForMajor":[],"notForProgramme":[],"notes":[],"onlyForCollege":[],"onlyForDegree":[],"onlyForMajor":[],"onlyForProgramme":[],"room":"1301","time":["14:00","16:50"]},{"building":"AC2","date":["2013-06-09T16:00:00.000Z","2013-07-27T15:59:59.999Z"],"day":["R"],"instructors":["KWOK Che Shan"],"mediumOfInstruction":null,"notForCollege":[],"notForDegree":[],"notForMajor":[],"notForProgramme":[],"notes":[],"onlyForCollege":[],"onlyForDegree":[],"onlyForMajor":[],"onlyForProgramme":[],"room":"1301","time":["19:00","21:50"]}],"levels":["A","B"],"section":"C62","waitlistAvailable":"N","webEnabled":true}],"title":"Appreciation of Built Heritage"}