{"academicUnit":"Systems Engg and Engg Mgt","code":"GE2328","exclusiveCourses":[],"prerequisites":null,"prerequisitesPostfix":[],"registrationDetail":[{"cohort":"2014","headcount":1,"major":"TVB","programme":"BA2"},{"cohort":"2014","headcount":1,"major":"ELST","programme":"BA4"},{"cohort":"2014","headcount":1,"major":"CB","programme":"BBA2"},{"cohort":"2013","headcount":1,"major":"BE","programme":"BBA3"},{"cohort":"2013","headcount":1,"major":"AC","programme":"BBA4"},{"cohort":"2014","headcount":1,"major":"AC","programme":"BBA4"},{"cohort":"2012","headcount":1,"major":"CB","programme":"BBA4"},{"cohort":"2014","headcount":1,"major":"CB","programme":"BBA4"},{"cohort":"2013","headcount":1,"major":"FIN","programme":"BBA4"},{"cohort":"2013","headcount":1,"major":"IB","programme":"BBA4"},{"cohort":"2014","headcount":1,"major":"IB","programme":"BBA4"},{"cohort":"2014","headcount":1,"major":"MIM","programme":"BBA4"},{"cohort":"2014","headcount":1,"major":"MKT1","programme":"BBA4"},{"cohort":"2015","headcount":1,"major":"IB","programme":"BBAU2"},{"cohort":"2015","headcount":3,"major":"U","programme":"BBAU4"},{"cohort":"2015","headcount":5,"major":"U","programme":"BDCLASS"},{"cohort":"2015","headcount":1,"major":"U","programme":"BDEE"},{"cohort":"2015","headcount":1,"major":"U","programme":"BDMBE"},{"cohort":"2013","headcount":1,"major":"ECE","programme":"BENG4"},{"cohort":"2012","headcount":2,"major":"IEEM","programme":"BENG4"},{"cohort":"2014","headcount":2,"major":"MFSE","programme":"BENG4"},{"cohort":"2013","headcount":1,"major":"TQE","programme":"BENG4"},{"cohort":"2015","headcount":1,"major":"ESE","programme":"BENGSEEU4"},{"cohort":"2015","headcount":1,"major":"TQE","programme":"BENGU3"},{"cohort":"2014","headcount":3,"major":"ESM","programme":"BSC4"},{"cohort":"2014","headcount":1,"major":"CRIM","programme":"BSS2"},{"cohort":"2014","headcount":1,"major":"PP","programme":"BSS4"},{"cohort":"2012","headcount":2,"major":"PPMP","programme":"BSS4"},{"cohort":"2014","headcount":2,"major":"SW","programme":"BSS4"},{"cohort":"0000","headcount":1,"major":"0000","programme":"EXFB"},{"cohort":"0000","headcount":7,"major":"0000","programme":"EXGB"}],"sections":[{"availableSeats":41,"availableWaitlistQuota":0,"campus":"Main Campus","capacity":90,"credit":3,"crn":46066,"groups":[{"building":"AC1","date":["2015-08-30T16:00:00.000Z","2015-11-28T15:59:59.999Z"],"day":["T"],"instructors":["NGAN Shing Chung S."],"mediumOfInstruction":null,"notForCollege":[],"notForDegree":[],"notForMajor":[],"notForProgramme":[],"notes":[],"onlyForCollege":[],"onlyForDegree":[],"onlyForMajor":[],"onlyForProgramme":[],"room":"LT-15","time":["09:00","11:50"]}],"levels":["B"],"section":"C01","waitlistAvailable":"N","webEnabled":true}],"title":"Understanding and Improving Enterprises for Future Leaders"}