{"academicUnit":"English","code":"GE2409","exclusiveCourses":[],"prerequisites":"EL0200 or EL0200E or EL0200X or (EL0220 and EL0222 and EL0223 and EL0225)","prerequisitesPostfix":["EL0200","EL0200E","or","EL0200X","or","EL0220","EL0222","and","EL0223","and","EL0225","and","or"],"registrationDetail":[{"cohort":"2014","headcount":1,"major":"ELST","programme":"BA2"},{"cohort":"2014","headcount":2,"major":"MDCM","programme":"BA3"},{"cohort":"2013","headcount":4,"major":"CRM","programme":"BASCM4"},{"cohort":"2015","headcount":4,"major":"CRM","programme":"BASCMU2"},{"cohort":"2015","headcount":2,"major":"ELST","programme":"BAU2"},{"cohort":"2015","headcount":2,"major":"LLA","programme":"BAU2"},{"cohort":"2015","headcount":2,"major":"MDCM","programme":"BAU2"},{"cohort":"2015","headcount":1,"major":"TVB","programme":"BAU2"},{"cohort":"2014","headcount":1,"major":"CRM1","programme":"BSCSCM3"},{"cohort":"2012","headcount":1,"major":"CRM1","programme":"BSCSCM4"},{"cohort":"2013","headcount":1,"major":"CRM1","programme":"BSCSCM4"},{"cohort":"2014","headcount":1,"major":"CRM1","programme":"BSCSCM4"},{"cohort":"2015","headcount":2,"major":"CRM1","programme":"BSCSCMU2"},{"cohort":"2014","headcount":3,"major":"ASOC","programme":"BSS2"},{"cohort":"2014","headcount":2,"major":"CRIM","programme":"BSS2"},{"cohort":"2013","headcount":1,"major":"ENP","programme":"BSS2"},{"cohort":"2014","headcount":2,"major":"PPMP","programme":"BSS2"},{"cohort":"2015","headcount":2,"major":"ASIS","programme":"BSSU2"},{"cohort":"2015","headcount":1,"major":"ASOC","programme":"BSSU2"},{"cohort":"2015","headcount":3,"major":"CRIM","programme":"BSSU2"},{"cohort":"2015","headcount":1,"major":"CRIM","programme":"BSSU3"},{"cohort":"2015","headcount":3,"major":"0000","programme":"ELAC"},{"cohort":"0000","headcount":6,"major":"0000","programme":"EXGB"}],"sections":[{"availableSeats":1,"availableWaitlistQuota":0,"campus":"Main Campus","capacity":25,"credit":3,"crn":48083,"groups":[{"building":"AC1","date":["2015-08-30T16:00:00.000Z","2015-11-28T15:59:59.999Z"],"day":["F"],"instructors":["LOU Jackie Jia"],"mediumOfInstruction":null,"notForCollege":[],"notForDegree":[],"notForMajor":[],"notForProgramme":[],"notes":[],"onlyForCollege":[],"onlyForDegree":["BA2","BA3","BA4","BAS2","BAS3","BAS4","BASCM2","BASCM3","BASCM4","BASCMU2","BASCMU3","BASU2","BASU3","BAU2","BAU3","BSCSCM2","BSCSCM3","BSCSCM4","BSCSCMU2","BSCSCMU3","BSS2","BSS3","BSS4","BSSU2","BSSU3"],"onlyForMajor":[],"onlyForProgramme":[],"room":"B5-416","time":["12:00","14:50"]}],"levels":["B"],"section":"T02","waitlistAvailable":"N","webEnabled":true},{"availableSeats":1,"availableWaitlistQuota":0,"campus":"Main Campus","capacity":25,"credit":3,"crn":48084,"groups":[{"building":"AC1","date":["2015-08-30T16:00:00.000Z","2015-11-28T15:59:59.999Z"],"day":["R"],"instructors":["YAU Hoi Ying Alice"],"mediumOfInstruction":null,"notForCollege":[],"notForDegree":[],"notForMajor":[],"notForProgramme":[],"notes":[],"onlyForCollege":[],"onlyForDegree":["BA2","BA3","BA4","BAS2","BAS3","BAS4","BASCM2","BASCM3","BASCM4","BASCMU2","BASCMU3","BASU2","BASU3","BAU2","BAU3","BSCSCM2","BSCSCM3","BSCSCM4","BSCSCMU2","BSCSCMU3","BSS2","BSS3","BSS4","BSSU2","BSSU3"],"onlyForMajor":[],"onlyForProgramme":[],"room":"Y5-409","time":["12:00","14:50"]}],"levels":["B"],"section":"T03","waitlistAvailable":"N","webEnabled":true}],"title":"Words and Images: Reading and Writing in the 21st Century"}